loci/__init__.py
loci/__main__.py
loci/check.py
loci/config.py
loci/login.py
loci/main.py
loci/project.py
loci/resources.py
loci/semgrep.py
loci/setup.py
loci/sync.py
loci/upload.py
loci/utils.py
loci/version.py
loci_cli-0.20241001.33235.dist-info/LICENSE
loci_cli-0.20241001.33235.dist-info/METADATA
loci_cli-0.20241001.33235.dist-info/WHEEL
loci_cli-0.20241001.33235.dist-info/entry_points.txt
loci_cli-0.20241001.33235.dist-info/RECORD
